{
    "035_mask":[
        {"chance":80,"vec":[-7682,464,118],"ang":[0,0,0],"comment":"text"}
    ],
    "weapon_hkp2000":[
        {"vec":[-11001,-2873,-968],"ang":[0,0,0],"comment":"Харда: Оружейка охраны."}
    ],
    "weapon_usp_silencer":[
    ],
    "weapon_fiveseven":[
        {"chance":100,"vec":[-11374,-2826,-978],"ang":[0,90,0],"comment":"Харда: Оружейка охраны."}
    ],
    "weapon_glock":[
        {"chance":40,"vec":[-2309,-2830,40],"ang":[0,-90,0],"comment":"Лайт: В офисах."},
        {"chance":100,"vec":[-5862,-1563,37],"ang":[0,180,0],"comment":"Лайт: Оружейка в легкой зоне."},
        {"chance":100,"vec":[-8363,1173,29],"ang":[0,97,0],"comment":"Харда: 049."},
        {"chance":80,"vec":[-11307,788,-367],"ang":[0,-77,0],"comment":"Харда: 106."}
    ],
    "weapon_tec9":[
    ],
    "weapon_elite":[
        {"chance":100,"vec":[-9387,2386,36],"ang":[0,-85,0],"comment":"Харда: Оружейка."},
        {"chance":60,"vec":[-7892,-5579,202],"ang":[0,91,0],"comment":"Харда: Боеголовка."}
    ],
    "weapon_p250":[
    ],
    "weapon_cz75a":[
        {"chance":100,"vec":[-9461,2386,36],"ang":[0,-95,0],"comment":"Харда: Оружейка."}
    ],
    "weapon_deagle":[
        {"chance":47,"vec":[-2116,-6566,259],"ang":[60,90,0],"comment":"Лайт: В комнате управления у дэшек."}
    ],
    "weapon_revolver":[
        {"chance":100,"vec":[-11414,-2825,-978],"ang":[0,90,0],"comment":"Харда: Оружейка охраны."}
    ],
    "weapon_mag7":[
    ],
    "weapon_sawedoff":[
    ],
    "weapon_nova":[
        {"chance":100,"vec":[-9608,2359,35],"ang":[0,90,0],"comment":"Харда: Оружейка."}
    ],
    "weapon_xm1014":[
    ],
    "weapon_mp9":[
    ],
    "weapon_mac10":[
    ],
    "weapon_mp7":[
        {"chance":100,"vec":[-5765,-1759,22],"ang":[0,-176,0],"comment":"Лайт: Оружейка в легкой зоне."}
    ],
    "weapon_mp5sd":[
    ],
    "weapon_ump45":[
    ],
    "weapon_p90":[
    ],
    "weapon_bizon":[
        {"chance":100,"vec":[-9608,2426,35],"ang":[0,90,0],"comment":"Харда: Оружейка."}
    ],
    "weapon_famas":[
    ],
    "weapon_m4a1_silencer":[
    ],
    "weapon_m4a1":[
        {"chance":100,"vec":[-10784,-3024,-978],"ang":[0,0,0],"comment":"Харда: Оружейка охраны."}
    ],
    "weapon_aug":[
    ],
    "weapon_galilar":[
    ],
    "weapon_ak47":[
        {"chance":100,"vec":[-11382,-3018,-978],"ang":[0,-180,0],"comment":"Харда: Оружейка охраны."}
    ],
    "weapon_sg556":[
    ],
    "weapon_scar20":[
    ],
    "weapon_g3sg1":[
    ],
    "weapon_ssg08":[
    ],
    "weapon_awp":[
        {"chance":100,"vec":[-10786,-2830,-978],"ang":[0,0,0],"comment":"Харда: Оружейка охраны."}
    ],
    "weapon_m249":[
    ],
    "weapon_negev":[
    ],
    "weapon_flashbang":[
        {"chance":77,"vec":[-762,-5545,-32],"ang":[0,91,0],"comment":"Лайт: За клеткой компа."},
        {"chance":43,"vec":[2982,-2732,0],"ang":[0,2,0],"comment":"Лайт: 914."},
        {"chance":25,"vec":[2982,-2732,5],"ang":[0,2,0],"comment":"Лайт: 914."},
        {"chance":54,"vec":[2612,-1358,24],"ang":[0,-179,0],"comment":"Лайт: В раздевалке."},
        {"chance":100,"vec":[-5854,-1766,46],"ang":[0,83,0],"comment":"Лайт: Оружейка в легкой зоне."},
        {"chance":100,"vec":[-5827,-1768,46],"ang":[0,83,0],"comment":"Лайт: Оружейка в легкой зоне."},
        {"chance":76,"vec":[-6813,-1675,1],"ang":[0,93,0],"comment":"Харда: Темный куб."},
        {"chance":100,"vec":[-9563,2491,4],"ang":[0,89,0],"comment":"Харда: Оружейка."},
        {"chance":100,"vec":[-9548,2511,4],"ang":[0,6,0],"comment":"Харда: Оружейка."},
        {"chance":100,"vec":[-9573,2516,4],"ang":[0,30,0],"comment":"Харда: Оружейка."},
        {"chance":100,"vec":[-10900,-3121,-998],"ang":[0,90,0],"comment":"Харда: Оружейка охраны."},
        {"chance":100,"vec":[-10954,-3121,-998],"ang":[0,90,0],"comment":"Харда: Оружейка охраны."}
    ],
    "weapon_hegrenade":[
        {"chance":42,"vec":[995,-1955,0],"ang":[0,176,0],"comment":"Лайт: Серверная."},
        {"chance":100,"vec":[-10870,-3121,-998],"ang":[0,90,0],"comment":"Харда: Оружейка охраны."},
        {"chance":100,"vec":[-10937,-3121,-998],"ang":[0,90,0],"comment":"Харда: Оружейка охраны."}
    ],
    "`weapon_incgrenade`":[
        {"chance":65,"vec":[-5850,-7456,42],"ang":[0,-1,0],"comment":"Лайт: В мед блоке."},
        {"chance":100,"vec":[-9490,2226,22],"ang":[0,94,0],"comment":"Харда: Оружейка."},
        {"chance":100,"vec":[-9511,2219,42],"ang":[0,94,0],"comment":"Харда: Оружейка."},
        {"chance":100,"vec":[-10911,-3121,-998],"ang":[0,90,0],"comment":"Харда: Оружейка охраны."},
        {"chance":100,"vec":[-10967,-3121,-998],"ang":[0,90,0],"comment":"Харда: Оружейка охраны."}
    ],
    "weapon_decoy":[
        {"chance":100,"vec":[-6147,-1663,46],"ang":[0,0,0],"comment":"Лайт: Оружейка в легкой зоне."}
    ],
    "weapon_smokegrenade":[
        {"chance":42,"vec":[631,-3436,43],"ang":[0,-92,0],"comment":"Лайт: В строящемся кубе."},
        {"chance":65,"vec":[965,-2455,108],"ang":[0,180,0],"comment":"Лайт: Серверная."},
        {"chance":100,"vec":[-6147,-1689,46],"ang":[0,0,0],"comment":"Лайт: Оружейка в легкой зоне."},
        {"chance":12,"vec":[-5397,2757,36],"ang":[0,-93,0],"comment":"Харда: SCP-996."},
        {"chance":100,"vec":[-9548,2220,42],"ang":[0,82,0],"comment":"Харда: Оружейка."},
        {"chance":100,"vec":[-9569,2223,42],"ang":[0,81,0],"comment":"Харда: Оружейка."},
        {"chance":81,"vec":[-8496,-5366,0],"ang":[0,37,0],"comment":"Харда: Боеголовка."},
        {"chance":100,"vec":[-10884,-3121,-998],"ang":[0,90,0],"comment":"Харда: Оружейка охраны."},
        {"chance":100,"vec":[-10943,-3121,-998],"ang":[0,90,0],"comment":"Харда: Оружейка охраны."}
    ],
    "weapon_healthshot":[
        {"chance":69,"vec":[-6668,-7378,32],"ang":[0,-49,0],"comment":"Лайт: В мед блоке."},
        {"chance":52,"vec":[-6650,-7363,32],"ang":[0,-50,0],"comment":"Лайт: В мед блоке."},
        {"chance":31,"vec":[-1033,-4700,80],"ang":[0,-93,0],"comment":"Лайт: В шкафу у компа."},
        {"chance":13,"vec":[3005,-2695,232],"ang":[0,90,0],"comment":"Лайт: 914."},
        {"chance":75,"vec":[-1609,-2520,64],"ang":[0,93,0],"comment":"Лайт: Комната отдыха."},
        {"chance":32,"vec":[-1642,-2520,64],"ang":[0,91,0],"comment":"Лайт: Комната отдыха."},
        {"chance":10,"vec":[-2034,-2053,0],"ang":[0,0,0],"comment":"Лайт: Комната отдыха."},
        {"chance":100,"vec":[-5956,-1435,46],"ang":[0,-90,0],"comment":"Лайт: Оружейка в легкой зоне."},
        {"chance":100,"vec":[-5972,-1435,46],"ang":[0,-90,0],"comment":"Лайт: Оружейка в легкой зоне."},
        {"chance":100,"vec":[-5988,-1435,46],"ang":[0,-90,0],"comment":"Лайт: Оружейка в легкой зоне."},
        {"chance":42,"vec":[-8181,142,271],"ang":[0,0,0],"comment":"Харда: 035, управление."},
        {"chance":76,"vec":[-8181,190,271],"ang":[0,0,0],"comment":"Харда: 035, управление."},
        {"chance":100,"vec":[-9208,2270,35],"ang":[0,180,0],"comment":"Харда: Оружейка."},
        {"chance":100,"vec":[-9208,2337,35],"ang":[0,180,0],"comment":"Харда: Оружейка."},
        {"chance":100,"vec":[-9209,2402,35],"ang":[0,180,0],"comment":"Харда: Оружейка."},
        {"chance":100,"vec":[-9209,2467,35],"ang":[0,180,0],"comment":"Харда: Оружейка."},
        {"chance":100,"vec":[-9208,2532,35],"ang":[0,180,0],"comment":"Харда: Оружейка."},
        {"chance":49,"vec":[-10321,185,29],"ang":[0,-1,0],"comment":"Харда: 106."},
        {"chance":50,"vec":[-10205,-2858,-967],"ang":[0,-1,0],"comment":"Харда: Кухня охраны."},
        {"chance":100,"vec":[-11185,-3120,-998],"ang":[0,90,0],"comment":"Харда: Оружейка охраны."},
        {"chance":100,"vec":[-11204,-3120,-998],"ang":[0,90,0],"comment":"Харда: Оружейка охраны."},
        {"chance":100,"vec":[-11216,-3120,-998],"ang":[0,90,0],"comment":"Харда: Оружейка охраны."},
        {"chance":100,"vec":[-11227,-3120,-998],"ang":[0,90,0],"comment":"Харда: Оружейка охраны."},
        {"chance":100,"vec":[-11247,-3120,-998],"ang":[0,90,0],"comment":"Харда: Оружейка охраны."},
        {"chance":100,"vec":[-11264,-3120,-998],"ang":[0,90,0],"comment":"Харда: Оружейка охраны."},
        {"chance":100,"vec":[-11276,-3120,-998],"ang":[0,90,0],"comment":"Харда: Оружейка охраны."},
        {"chance":100,"vec":[-11293,-3120,-998],"ang":[0,90,0],"comment":"Харда: Оружейка охраны."},
        {"chance":13,"vec":[-8673,-6566,1882],"ang":[0,0,0],"comment":"Выход: Б."}
    ],
    "500_panacea":[
        {"chance":75,"vec":[-5396,2770,36],"ang":[0,0,0],"comment":"Харда: SCP-996."}
    ],
    "427_amulet":[
        {"chance":25,"vec":[-6795,-1726,1],"ang":[0,90,0],"comment":"Харда"}
    ],
    "268_cap":[
        {"chance":75,"vec":[-10556,29,37],"ang":[0,0,0],"comment":"Харда: SCP-106."}
    ],
    "005_picklock":[
        {
            "29":{"vec":[-7332,-2427,36],"ang":[0,0,0]},
            "31":{"vec":[-6304,-5466,36],"ang":[0,0,0]},
            "40":{"vec":[-296,-1074,30],"ang":[0,0,0]}
        }
    ],
    "weapon_axe":[
        {"chance":32,"vec":[-4174,-5820,32],"ang":[0,97,84],"comment":"Лайт: На складе № D."}
    ],
    "weapon_hammer":[
        {"chance":75,"vec":[954,-3283,51],"ang":[0,-177,0],"comment":"Лайт: В строящемся кубе."},
        {"chance":80,"vec":[3803,-2645,79],"ang":[0,90,0],"comment":"Лайт: 914."},
        {"chance":45,"vec":[-4182,-5838,32],"ang":[0,70,-90],"comment":"Лайт: На складе № D."}
    ],
    "weapon_spanner":[
        {"chance":22,"vec":[-1949,-5865,0],"ang":[0,-90,0],"comment":"Лайт: Душевая у дэшек."},
        {"chance":42,"vec":[911,-3332,28],"ang":[0,67,0],"comment":"Лайт: В строящемся кубе."},
        {"chance":76,"vec":[237,-3644,0],"ang":[0,35,0],"comment":"Лайт: В строящемся кубе."}
    ],
    "weapon_breachcharge":[
        {"chance":30,"vec":[-3514,-1166,57],"ang":[0,-179,0],"comment":"Лайт: На складе №173."}
    ],
    "weapon_shield":[
    ],
    "weapon_bumpmine":[
    ],
    "plastic":[
        {"chance":65,"vec":[-3669,-1455,56],"ang":[0,87,90],"comment":"Лайт: На складе №173."},
        {"chance":20,"vec":[-3362,-1298,56],"ang":[0,180,90],"comment":"Лайт: На складе №173."},
        {"chance":72,"vec":[-3362,-1297,56],"ang":[0,-179,90],"comment":"Лайт: На складе №173."},
        {"chance":10,"vec":[-4135,-5978,56],"ang":[0,180,90],"comment":"Лайт: На складе № D."},
        {"chance":90,"vec":[-4448,-5502,56],"ang":[0,180,90],"comment":"Лайт: На складе № D."}
        
    ],
    "iron_ingot":[
        {"chance":85,"vec":[-769,-5346,30],"ang":[0,-6,0],"comment":"Лайт: За компом."},
        {"chance":40,"vec":[-769,-5346,33],"ang":[0,-6,0],"comment":"Лайт: За компом."},
        {"chance":70,"vec":[-3513,-1461,56],"ang":[0,-2,0],"comment":"Лайт: На складе №173."},
        {"chance":30,"vec":[-3513,-1461,76],"ang":[0,2,0],"comment":"Лайт: На складе №173."},
        {"chance":20,"vec":[-4294,-5671,56],"ang":[0,180,0],"comment":"Лайт: На складе № D."},
        {"chance":60,"vec":[-4294,-5671,76],"ang":[0,180,0],"comment":"Лайт: На складе № D."}
    ],
    "card_janitor":[
        {"chance":50,"vec":[-2154,-4428,10],"ang":[0,-179,0],"comment":"Лайт: Под лестницей у дешек."},
        {"chance":30,"vec":[2300,-1176,24],"ang":[0,-34,0],"comment":"Лайт: В раздевалке."},
        {"chance":100,"vec":[-1958,-1006,0],"ang":[0,175,0],"comment":"Лайт: 173 внутри"},
        {"chance":35,"vec":[-1844,-5950,24],"ang":[70,179,0], "comment":"¯\\_(ツ)_/¯"},
        {"chance":35,"vec":[-1903,-6469,270],"ang":[38,-89,0], "comment":"¯\\_(ツ)_/¯"},
        {"chance":35,"vec":[-2678,-3042,55],"ang":[74,90,0], "comment":"¯\\_(ツ)_/¯"},
        {"chance":35,"vec":[-1953,-2518,79],"ang":[61,2,0], "comment":"¯\\_(ツ)_/¯"},
        {"chance":35,"vec":[-1866,-1929,79],"ang":[63,-178,0], "comment":"¯\\_(ツ)_/¯"},
        {"chance":35,"vec":[-1535,-2329,18],"ang":[81,-90,0], "comment":"¯\\_(ツ)_/¯"},
        {"chance":35,"vec":[-4021,-5838,79],"ang":[69,-90,0], "comment":"¯\\_(ツ)_/¯"},
        {"chance":35,"vec":[-4444,-5836,79],"ang":[78,-90,0], "comment":"¯\\_(ツ)_/¯"},
        {"chance":35,"vec":[-4270,-5835,79],"ang":[82,89,0], "comment":"¯\\_(ツ)_/¯"},
        {"chance":35,"vec":[-1633,-650,274],"ang":[87,-1,0], "comment":"¯\\_(ツ)_/¯"},
        {"chance":35,"vec":[-2243,-3342,47],"ang":[77,165,0], "comment":"¯\\_(ツ)_/¯"},
        {"chance":35,"vec":[1152,-2510,0],"ang":[79,139,0], "comment":"¯\\_(ツ)_/¯"}
    ],
    "card_scientist":[
        {"chance":100,"vec":[-6916,-7454,32],"ang":[0,87,0],"comment":"Лайт: В мед блоке."},
        {"chance":50,"vec":[578, -3444, 43],"ang":[0,87,0],"comment":"Лайт: В строящемся кубе."},
        {"chance":20,"vec":[2713,-2394,287],"ang":[0,0,0],"comment":"Лайт: 914."},
        {"chance":45,"vec":[-2732,-3137,2],"ang":[0,-89,0],"comment":"Лайт: В офисах."}
    ],
    "card_major_scientist":[
        {"chance":30,"vec":[-1235,-2515,27],"ang":[0,49,0],"comment":"Лайт: Комната отдыха."},
        {"chance":99,"vec":[-8758,1242,36],"ang":[0,178,0],"comment":"Харда: 049."}
    ],
    "card_zone_manager":[
        {"chance":35,"vec":[-2038,-656,264],"ang":[0,-91,0],"comment":"Лайт: 173 пульт."}
    ],
    "card_guard":[
    ],
    "card_senior_guard":[
    ],
    "card_mog_lieutenant":[
        {"chance":75,"vec":[-13026,-2369,0],"ang":[0,-93,0],"comment":"Харда: 096."}
    ],
    "flashlight":[
        {"chance":100,"vec":[-10746,-3027,-978],"ang":[60,-180,0],"comment":"Харда: Оружейка охраны."},
        {"chance":100,"vec":[-10813,-2829,-978],"ang":[60,0,0],"comment":"Харда: Оружейка охраны."},
        {"chance":75,"vec":[-2115,-6722,259],"ang":[60,90,0],"comment":"Лайт: В комнате управления у дэшек."}
    ],
    "radio":[
        {"chance":45,"vec":[-1913,-6185,251],"ang":[75,0,0],"comment":"Лайт: В комнате управления у дэшек."},
        {"chance":100,"vec":[-5982,-6175,32],"ang":[79,172,0],"comment":"Офисы: Интерком."}
    ]
}